nonebot_plugin_distributed_blacklist/__init__.py
nonebot_plugin_distributed_blacklist/api.py
nonebot_plugin_distributed_blacklist/config.py
nonebot_plugin_distributed_blacklist/core.py
nonebot_plugin_distributed_blacklist/database.py
nonebot_plugin_distributed_blacklist/kick_manager.py
nonebot_plugin_distributed_blacklist/schedule.py
nonebot_plugin_distributed_blacklist-1.0.5.dist-info/licenses/LICENSE
nonebot_plugin_distributed_blacklist-1.0.5.dist-info/METADATA
nonebot_plugin_distributed_blacklist-1.0.5.dist-info/WHEEL
nonebot_plugin_distributed_blacklist-1.0.5.dist-info/top_level.txt
nonebot_plugin_distributed_blacklist-1.0.5.dist-info/RECORD
