Metadata-Version: 2.4
Name: nonebot-plugin-distributed-blacklist
Version: 1.0.5
Summary: 基于PostgreSQL的分布式黑名单系统
Home-page: https://github.com/your-repo/nonebot-plugin-distributed-blacklist
Author: Tosd0
Author-email: Tosd0 <tntobsidian@126.com>
License: LGPL-3.0
Project-URL: Homepage, https://github.com/Tosd0/nonebot-plugin-distributed-blacklist
Project-URL: Repository, https://github.com/Tosd0/nonebot-plugin-distributed-blacklist
Project-URL: Documentation, https://github.com/Tosd0/nonebot-plugin-distributed-blacklist
Project-URL: Issues, https://github.com/Tosd0/nonebot-plugin-distributed-blacklist/issues
Keywords: nonebot,blacklist,distributed,postgresql
Classifier: License :: OSI Approved :: GNU Lesser General Public License v3 (LGPLv3)
Classifier: Operating System :: OS Independent
Classifier: Programming Language :: Python :: 3
Classifier: Programming Language :: Python :: 3.9
Classifier: Programming Language :: Python :: 3.10
Classifier: Programming Language :: Python :: 3.11
Classifier: Programming Language :: Python :: 3.12
Requires-Python: >=3.9
License-File: LICENSE
Requires-Dist: nonebot2<3.0.0,>=2.3.0
Requires-Dist: nonebot-adapter-onebot>=2.3.0
Requires-Dist: nonebot-plugin-apscheduler>=0.5.0
Requires-Dist: nonebot-plugin-localstore>=0.6.0
Requires-Dist: asyncpg>=0.28.0
Requires-Dist: pydantic>=1.10.0
Provides-Extra: dev
Requires-Dist: pytest; extra == "dev"
Requires-Dist: pytest-asyncio; extra == "dev"
Requires-Dist: black; extra == "dev"
Requires-Dist: isort; extra == "dev"
Requires-Dist: flake8; extra == "dev"
Dynamic: author
Dynamic: home-page
Dynamic: license-file
Dynamic: requires-python
